lpf_mcp_demo/__init__.py
lpf_mcp_demo-0.1.0.dist-info/METADATA
lpf_mcp_demo-0.1.0.dist-info/WHEEL
lpf_mcp_demo-0.1.0.dist-info/entry_points.txt
lpf_mcp_demo-0.1.0.dist-info/RECORD
