Metadata-Version: 2.4
Name: lpf-mcp-demo
Version: 0.1.0
Summary: Add your description here
Author-email: liupengfei <lpf940528@gmail.com>
Requires-Python: >=3.12
Requires-Dist: mcp[cli]>=1.25.0
